nannos/__about__.py
nannos/__init__.py
nannos/constants.py
nannos/excitation.py
nannos/geometry.py
nannos/lattice.py
nannos/layers.py
nannos/log.py
nannos/optimize.py
nannos/parallel.py
nannos/plot.py
nannos/sample.py
nannos/simulation.py
nannos/formulations/__init__.py
nannos/formulations/fft.py
nannos/formulations/jones.py
nannos/formulations/tangent.py
nannos/utils/__init__.py
nannos/utils/helpers.py
nannos/utils/jupyter.py
nannos/utils/time.py
nannos-2.6.3.dist-info/LICENSE.txt
nannos-2.6.3.dist-info/METADATA
nannos-2.6.3.dist-info/WHEEL
nannos-2.6.3.dist-info/dependency_links.txt
nannos-2.6.3.dist-info/top_level.txt
nannos-2.6.3.dist-info/RECORD
