Metadata-Version: 2.1
Name: nannos
Version: 2.6.3
Summary: Fourier Modal Method for multilayer metamaterials
Home-page: https://gitlab.com/nannos/nannos
Author: Benjamin Vial
License: GPL-3.0-or-later
Project-URL: Code, https://gitlab.com/nannos/nannos
Project-URL: Documentation, https://nannos.gitlab.io
Project-URL: Issues, https://gitlab.com/nannos/nannos/issues
Keywords: fourier modal method,diffraction,optics,photonics,metamaterials
Classifier: Development Status :: 4 - Beta
Classifier: Intended Audience :: Science/Research
Classifier: License :: OSI Approved :: GNU General Public License v3 or later (GPLv3+)
Classifier: Operating System :: OS Independent
Classifier: Programming Language :: Python
Classifier: Programming Language :: Python :: 3
Classifier: Programming Language :: Python :: 3.8
Classifier: Programming Language :: Python :: 3.9
Classifier: Topic :: Scientific/Engineering
Classifier: Topic :: Scientific/Engineering :: Mathematics
Classifier: Topic :: Utilities
Requires-Python: >=3.6
License-File: LICENSE.txt
Requires-Dist: numpy >=1.9
Requires-Dist: scipy >=1.0
Requires-Dist: autograd >=1.6.2
Requires-Dist: joblib
Requires-Dist: colorlog
Requires-Dist: shapely
Requires-Dist: psutil
Requires-Dist: ipython
Requires-Dist: matplotlib
Requires-Dist: pyvista[jupyter] >=0.43.1
Requires-Dist: trame
Requires-Dist: ipywidgets
Requires-Dist: importlib-metadata ; python_version < "3.8"
Provides-Extra: all
Requires-Dist: nannos[backends] ; extra == 'all'
Requires-Dist: nannos[gpu] ; extra == 'all'
Requires-Dist: nannos[magma] ; extra == 'all'
Requires-Dist: nannos[opt] ; extra == 'all'
Provides-Extra: backends
Requires-Dist: jax ; extra == 'backends'
Requires-Dist: jaxlib ; extra == 'backends'
Requires-Dist: torch ; extra == 'backends'
Provides-Extra: gpu
Requires-Dist: jax[cuda12_pip] ; extra == 'gpu'
Provides-Extra: magma
Requires-Dist: scikit-cuda ; extra == 'magma'
Provides-Extra: opt
Requires-Dist: nlopt ; extra == 'opt'
